ModuShell/8bit_colors.json
ModuShell/__init__.py
modushell-1.6.0.dist-info/licenses/LICENSE
modushell-1.6.0.dist-info/METADATA
modushell-1.6.0.dist-info/WHEEL
modushell-1.6.0.dist-info/top_level.txt
modushell-1.6.0.dist-info/RECORD
