Metadata-Version: 2.4
Name: ModuShell
Version: 1.6.0
Summary: ModuShell is a package that you can use to customize any outputs to the console using simple calls within format strings. Requires a modern terminal that can handle ANSI escape sequences.
Author-email: Kenneth Irving <contact.kenneth.irving@gmail.com>
License: MIT
Project-URL: Homepage, https://github.com/irvingkennet45/ModuShell
Project-URL: Repository, https://github.com/irvingkennet45/ModuShell
Project-URL: Bug Tracker, https://github.com/irvingkennet45/ModuShell/issues
Keywords: shell,cli,ansi,terminal,formatting,console,color,text styling,customize
Classifier: Programming Language :: Python :: 3
Classifier: Programming Language :: Python :: 3.7
Classifier: License :: OSI Approved :: MIT License
Classifier: Operating System :: OS Independent
Classifier: Intended Audience :: Developers
Classifier: Topic :: Software Development :: Libraries
Classifier: Topic :: Terminals
Classifier: Environment :: Console
Classifier: Development Status :: 5 - Production/Stable
Requires-Python: >=3.7
License-File: LICENSE
Dynamic: license-file
